semcache_rs/__init__.py
semcache_rs/__init__.pyi
semcache_rs/py.typed
semcache_rs/semcache_rs.cpython-314-darwin.so
semcache_rs-0.1.0.dist-info/METADATA
semcache_rs-0.1.0.dist-info/WHEEL
semcache_rs-0.1.0.dist-info/licenses/LICENSE
semcache_rs.pyi
semcache_rs-0.1.0.dist-info/RECORD
