Metadata-Version: 2.4
Name: semcache_rs
Version: 0.1.0
Classifier: Programming Language :: Rust
Classifier: Programming Language :: Python :: Implementation :: CPython
Classifier: Programming Language :: Python :: Implementation :: PyPy
License-File: LICENSE
Summary: High-performance, in-process embedding cache for LLMs. Powered by Rust & SIMD to reduce API costs and latency.
Requires-Python: >=3.8
